clerrit/__init__.py
clerrit/common.py
clerrit/fix.py
clerrit/review.py
clerrit-0.4.0.dist-info/METADATA
clerrit-0.4.0.dist-info/WHEEL
clerrit-0.4.0.dist-info/entry_points.txt
clerrit-0.4.0.dist-info/RECORD
