Metadata-Version: 2.4
Name: clerrit
Version: 0.4.0
Summary: Supercharge your Gerrit workflow with LLM-powered code reviews and fixes
Project-URL: Homepage, https://github.com/eepp/clerrit
Project-URL: Repository, https://github.com/eepp/clerrit
Project-URL: Issues, https://github.com/eepp/clerrit/issues
Author-email: Philippe Proulx <eeppeliteloop@gmail.com>
License-Expression: MIT
Keywords: claude,cli,code-review,gerrit,llm
Classifier: Development Status :: 4 - Beta
Classifier: Environment :: Console
Classifier: Intended Audience :: Developers
Classifier: License :: OSI Approved :: MIT License
Classifier: Programming Language :: Python :: 3.11
Classifier: Programming Language :: Python :: 3.12
Classifier: Programming Language :: Python :: 3.13
Classifier: Topic :: Software Development :: Version Control :: Git
Requires-Python: >=3.11
Requires-Dist: rich~=14.2
Requires-Dist: typer~=0.20
